[{"productId":"a","productName":"a","price":11.0,"seller":"seller","productStatus":"UNDERREVIEWFORCONSTRUCTION","category":{"name":"fff","traits":["a"]},"numberOfProducts":1,"isInSale":false,"numberOfViews":0,"totalNumberOfBuyers":0,"isBought":false,"inAuction":false,"productImageId":"C:\\Users\\ASA\\Pictures\\Saved Pictures\\74865_inspirational-laptop-backgrounds.jpg","categoryName":"fff","file":{"path":"C:\\Users\\ASA\\Documents\\2مطب.pdf"},"listOfBuyers":[],"proComments":[],"productCategorySpecifications":[],"score":0.0,"scorePeople":0,"firm":{"name":"a","phoneNO":0.0,"address":"a","type":"company"}}]